{"GID":"302947827","StoreID":"110","StoreName":"МАГАЗИН АНЕТ 4 бл.548","WorkstationID":"2","FiscalDeviceID":"DT938710","UserGID":"11","SaleID":"947827","SaleUniqueID":"DT938710-0011-0947827","ReceiptID":"430150","ClientGID":"1","ClientName":"КЛИЕНТ НА МАГАЗИН АНЕТ 4","ClientTaxNumberType":"0","ClientTaxNumber":"","ClientAddress":"","ClientReceiver":"","ClientBuyer":"","ClientVIPStatus":"","ClientSurcharge":"0.00","InvoiceID":"","InvoiceDate":"","CreatedDate":"08-06-24","CreatedTime":"08:55:25","CompletedDate":"08-06-24","CompletedTime":"08:56:25","TotalBase":"0.00","Discount":"0.00","TotalVAT":"0.00","Due":"12.04","CashPayment":"15.00","VoucherPayment":"0.00","CardPayment":"0.00","Returned":"2.96","Stage":"приключена","Details":[{"GID":"311771670","ParentGID":"302947827","SaleUniqueID":"DT938710-0011-0947827","UserGID":"11","CreatedDate":"08-06-24","CreatedTime":"08:55:25","SaleDate":"08-06-24","SaleTime":"08:55:25","Typed":"3800207280314","ItemGID":"100008758","BarCode":"3800207280314","BaseItemName":"ГАЗИРАНА НАПИТКА \"ЕЛИТ\" 3Л.ВИДОВЕ","PackCoeff":"1","ItemName":"ГАЗИРАНА НАПИТКА \"ЕЛИТ\" 3Л.ВИДОВЕ                                     ","Measure":"БР.","Quantity":"1.000","VendorPrice":"0.8800","ClientSurcharge":"0.00","ClientPrice":"1.08","PackDiscount":"0","ClientPriceBase":"0.90","Price":"1.08","DiscountValue":"0.00","DiscountType":"0","TotalBase":"0.90","VATRate":"20.00","TotalVAT":"0.18","Total":"1.08","IsCancelled":"не"},{"GID":"311771672","ParentGID":"302947827","SaleUniqueID":"DT938710-0011-0947827","UserGID":"11","CreatedDate":"08-06-24","CreatedTime":"08:55:25","SaleDate":"08-06-24","SaleTime":"08:55:28","Typed":"3800012140421","ItemGID":"100717002","BarCode":"3800012140421","BaseItemName":"ЛЮТЕНИЦА СЕЛЦЕ ТРАДИЦИОННА 1.080КГ.","PackCoeff":"1","ItemName":"ЛЮТЕНИЦА СЕЛЦЕ ТРАДИЦИОННА 1.080КГ.                                   ","Measure":"БР.","Quantity":"1.000","VendorPrice":"4.3450","ClientSurcharge":"0.00","ClientPrice":"5.19","PackDiscount":"0","ClientPriceBase":"4.33","Price":"5.19","DiscountValue":"0.00","DiscountType":"0","TotalBase":"4.33","VATRate":"20.00","TotalVAT":"0.86","Total":"5.19","IsCancelled":"не"},{"GID":"311771674","ParentGID":"302947827","SaleUniqueID":"DT938710-0011-0947827","UserGID":"11","CreatedDate":"08-06-24","CreatedTime":"08:55:25","SaleDate":"08-06-24","SaleTime":"08:55:50","Typed":"кюфт м р гри","ItemGID":"100709346","BarCode":"3800030003203","BaseItemName":"КЮФТЕ ЗА СКАРА 8Х40ГР.М-Р ГРИЛ","PackCoeff":"1","ItemName":"КЮФТЕ ЗА СКАРА 8Х40ГР.М-Р ГРИЛ                                        ","Measure":"БР.","Quantity":"1.000","VendorPrice":"1.7300","ClientSurcharge":"0.00","ClientPrice":"2.15","PackDiscount":"0","ClientPriceBase":"1.79","Price":"2.15","DiscountValue":"0.00","DiscountType":"0","TotalBase":"1.79","VATRate":"20.00","TotalVAT":"0.36","Total":"2.15","IsCancelled":"не"},{"GID":"311771676","ParentGID":"302947827","SaleUniqueID":"DT938710-0011-0947827","UserGID":"11","CreatedDate":"08-06-24","CreatedTime":"08:55:25","SaleDate":"08-06-24","SaleTime":"08:55:56","Typed":"2*3800212490890","ItemGID":"15592","BarCode":"3800212490890","BaseItemName":"КИСЕЛО МЛЯКО БОР ЧВОР 4.5%400ГР.","PackCoeff":"1","ItemName":"КИСЕЛО МЛЯКО БОР ЧВОР 4.5%400ГР.                                      ","Measure":"БР.","Quantity":"2.000","VendorPrice":"0.9000","ClientSurcharge":"0.00","ClientPrice":"1.05","PackDiscount":"0","ClientPriceBase":"0.88","Price":"1.05","DiscountValue":"0.00","DiscountType":"0","TotalBase":"1.75","VATRate":"20.00","TotalVAT":"0.35","Total":"2.10","IsCancelled":"не"},{"GID":"311771678","ParentGID":"302947827","SaleUniqueID":"DT938710-0011-0947827","UserGID":"11","CreatedDate":"08-06-24","CreatedTime":"08:55:25","SaleDate":"08-06-24","SaleTime":"08:55:58","Typed":"500","ItemGID":"2491","BarCode":"500","BaseItemName":"БЯЛ ХЛЯБ СЛАДКАР","PackCoeff":"1","ItemName":"БЯЛ ХЛЯБ СЛАДКАР                                                      ","Measure":"БР.","Quantity":"1.000","VendorPrice":"1.4000","ClientSurcharge":"0.00","ClientPrice":"1.52","PackDiscount":"0","ClientPriceBase":"1.52","Price":"1.52","DiscountValue":"0.00","DiscountType":"0","TotalBase":"1.52","VATRate":"0.00","TotalVAT":"0.00","Total":"1.52","IsCancelled":"не"}],"Cancellations":[],"Reversals":[],"Payments":[{"GID":"304167117","ParentGID":"302947827","SaleUniqueID":"DT938710-0011-0947827","FiscalDeviceID":"DT938710","UserID":"11","CreatedDate":"08-06-24","CompletedDate":"08-06-24","Due":"12.04","PaymentDate":"08-06-24","PaymentType":"cash","PaymentBase":"12.50","PaymentVAT":"2.50","Payment":"15.00"},{"GID":"304167118","ParentGID":"302947827","SaleUniqueID":"DT938710-0011-0947827","FiscalDeviceID":"DT938710","UserID":"11","CreatedDate":"08-06-24","CompletedDate":"08-06-24","Due":"12.04","PaymentDate":"08-06-24","PaymentType":"returned","PaymentBase":"2.47","PaymentVAT":"0.49","Payment":"2.96"}]}