{"GID":"302308052","StoreID":"110","StoreName":"МАГАЗИН АНЕТ 4 бл.548","WorkstationID":"2","FiscalDeviceID":"DT652293","UserGID":"6","SaleID":"308052","SaleUniqueID":"DT652293-0006-0308052","ReceiptID":"756379","ClientGID":"1","ClientName":"КЛИЕНТ НА МАГАЗИН АНЕТ 4","ClientTaxNumberType":"0","ClientTaxNumber":"","ClientAddress":"","ClientReceiver":"","ClientBuyer":"","ClientVIPStatus":"","ClientSurcharge":"0.00","InvoiceID":"","InvoiceDate":"","CreatedDate":"08-06-21","CreatedTime":"17:29:55","CompletedDate":"08-06-21","CompletedTime":"17:31:48","TotalBase":"0.00","Discount":"0.00","TotalVAT":"0.00","Due":"21.84","CashPayment":"22.00","VoucherPayment":"0.00","CardPayment":"0.00","Returned":"0.16","Stage":"приключена","Details":[{"GID":"305303376","ParentGID":"302308052","SaleUniqueID":"DT652293-0006-0308052","UserGID":"6","CreatedDate":"08-06-21","CreatedTime":"17:29:55","SaleDate":"08-06-21","SaleTime":"17:29:55","Typed":"3809612039371","ItemGID":"100076103","BarCode":"3809612039371","BaseItemName":"КИСЕЛО МЛЯКО ТОНУС 3.6% 400гр.","PackCoeff":"1","ItemName":"КИСЕЛО МЛЯКО ТОНУС 3.6% 400гр.                                        ","Measure":"БР.","Quantity":"1.000","VendorPrice":"0.8835","ClientSurcharge":"0.00","ClientPrice":"1.00","PackDiscount":"0","ClientPriceBase":"0.83","Price":"1.00","DiscountValue":"0.00","DiscountType":"0","TotalBase":"0.83","VATRate":"20.00","TotalVAT":"0.17","Total":"1.00","IsCancelled":"не"},{"GID":"305303378","ParentGID":"302308052","SaleUniqueID":"DT652293-0006-0308052","UserGID":"6","CreatedDate":"08-06-21","CreatedTime":"17:29:55","SaleDate":"08-06-21","SaleTime":"17:29:59","Typed":"7613036923293","ItemGID":"100482137","BarCode":"7613036923293","BaseItemName":"ВАФЛА МУРА БРАУНИ 33ГР.","PackCoeff":"1","ItemName":"ВАФЛА МУРА БРАУНИ 33ГР.                                               ","Measure":"БР.","Quantity":"1.000","VendorPrice":"0.3480","ClientSurcharge":"0.00","ClientPrice":"0.45","PackDiscount":"0","ClientPriceBase":"0.38","Price":"0.45","DiscountValue":"0.00","DiscountType":"0","TotalBase":"0.38","VATRate":"20.00","TotalVAT":"0.07","Total":"0.45","IsCancelled":"не"},{"GID":"305303380","ParentGID":"302308052","SaleUniqueID":"DT652293-0006-0308052","UserGID":"6","CreatedDate":"08-06-21","CreatedTime":"17:29:55","SaleDate":"08-06-21","SaleTime":"17:30:00","Typed":"7613036923293","ItemGID":"100482137","BarCode":"7613036923293","BaseItemName":"ВАФЛА МУРА БРАУНИ 33ГР.","PackCoeff":"1","ItemName":"ВАФЛА МУРА БРАУНИ 33ГР.                                               ","Measure":"БР.","Quantity":"1.000","VendorPrice":"0.3480","ClientSurcharge":"0.00","ClientPrice":"0.45","PackDiscount":"0","ClientPriceBase":"0.38","Price":"0.45","DiscountValue":"0.00","DiscountType":"0","TotalBase":"0.38","VATRate":"20.00","TotalVAT":"0.07","Total":"0.45","IsCancelled":"не"},{"GID":"305303382","ParentGID":"302308052","SaleUniqueID":"DT652293-0006-0308052","UserGID":"6","CreatedDate":"08-06-21","CreatedTime":"17:29:55","SaleDate":"08-06-21","SaleTime":"17:30:07","Typed":"38006487","ItemGID":"14984","BarCode":"38006487","BaseItemName":"ЯЙЦА L 10БР. ХАЙПРО\/ДАН-2000","PackCoeff":"1","ItemName":"ЯЙЦА L 10БР. ХАЙПРО\/ДАН-2000                                          ","Measure":"БР.","Quantity":"1.000","VendorPrice":"1.3500","ClientSurcharge":"0.00","ClientPrice":"1.55","PackDiscount":"0","ClientPriceBase":"1.29","Price":"1.55","DiscountValue":"0.00","DiscountType":"0","TotalBase":"1.29","VATRate":"20.00","TotalVAT":"0.26","Total":"1.55","IsCancelled":"не"},{"GID":"305303384","ParentGID":"302308052","SaleUniqueID":"DT652293-0006-0308052","UserGID":"6","CreatedDate":"08-06-21","CreatedTime":"17:29:55","SaleDate":"08-06-21","SaleTime":"17:30:11","Typed":"2402236002502","ItemGID":"2518","BarCode":"2402236","BaseItemName":"ТЕЛ. САЗДЪРМА АБВ ЗАГОРСКА","PackCoeff":"1","ItemName":"ТЕЛ. САЗДЪРМА АБВ ЗАГОРСКА                                            ","Measure":"КГ.","Quantity":"0.250","VendorPrice":"12.8000","ClientSurcharge":"0.00","ClientPrice":"14.80","PackDiscount":"0","ClientPriceBase":"12.33","Price":"14.80","DiscountValue":"0.00","DiscountType":"0","TotalBase":"3.08","VATRate":"20.00","TotalVAT":"0.62","Total":"3.70","IsCancelled":"не"},{"GID":"305303386","ParentGID":"302308052","SaleUniqueID":"DT652293-0006-0308052","UserGID":"6","CreatedDate":"08-06-21","CreatedTime":"17:29:55","SaleDate":"08-06-21","SaleTime":"17:30:13","Typed":"3800216170026","ItemGID":"100192359","BarCode":"3800216170026","BaseItemName":"РИБА ПЕРЛА 180ГР.\/ЕКОПРОМ","PackCoeff":"1","ItemName":"РИБА ПЕРЛА 180ГР.\/ЕКОПРОМ                                             ","Measure":"БР.","Quantity":"1.000","VendorPrice":"1.5500","ClientSurcharge":"0.00","ClientPrice":"1.85","PackDiscount":"0","ClientPriceBase":"1.54","Price":"1.85","DiscountValue":"0.00","DiscountType":"0","TotalBase":"1.54","VATRate":"20.00","TotalVAT":"0.31","Total":"1.85","IsCancelled":"не"},{"GID":"305303388","ParentGID":"302308052","SaleUniqueID":"DT652293-0006-0308052","UserGID":"6","CreatedDate":"08-06-21","CreatedTime":"17:29:55","SaleDate":"08-06-21","SaleTime":"17:30:18","Typed":"3800207712723","ItemGID":"100076367","BarCode":"3800207712723","BaseItemName":"ПЪЛНОЗЪРНЕСТ ХЛЯБ ДАРИЯ 600ГР.","PackCoeff":"1","ItemName":"ПЪЛНОЗЪРНЕСТ ХЛЯБ ДАРИЯ 600ГР.                                        ","Measure":"БР.","Quantity":"1.000","VendorPrice":"0.9500","ClientSurcharge":"0.00","ClientPrice":"1.05","PackDiscount":"0","ClientPriceBase":"0.88","Price":"1.05","DiscountValue":"0.00","DiscountType":"0","TotalBase":"0.88","VATRate":"20.00","TotalVAT":"0.17","Total":"1.05","IsCancelled":"не"},{"GID":"305303390","ParentGID":"302308052","SaleUniqueID":"DT652293-0006-0308052","UserGID":"6","CreatedDate":"08-06-21","CreatedTime":"17:29:55","SaleDate":"08-06-21","SaleTime":"17:30:23","Typed":"3800229785491","ItemGID":"100773357","BarCode":"3800229785491","BaseItemName":"КИСЕЛИ КРАСТАВИЧКИ АРТЕ 0.720МЛ.","PackCoeff":"1","ItemName":"КИСЕЛИ КРАСТАВИЧКИ АРТЕ 0.720МЛ.                                      ","Measure":"БР.","Quantity":"1.000","VendorPrice":"1.5550","ClientSurcharge":"0.00","ClientPrice":"1.85","PackDiscount":"0","ClientPriceBase":"1.54","Price":"1.85","DiscountValue":"0.00","DiscountType":"0","TotalBase":"1.54","VATRate":"20.00","TotalVAT":"0.31","Total":"1.85","IsCancelled":"не"},{"GID":"305303392","ParentGID":"302308052","SaleUniqueID":"DT652293-0006-0308052","UserGID":"6","CreatedDate":"08-06-21","CreatedTime":"17:29:55","SaleDate":"08-06-21","SaleTime":"17:30:27","Typed":"5449000203823","ItemGID":"100226148","BarCode":"5449000203823","BaseItemName":"ПЛОД.НАП.КАПИ ПРАСКОВА ПЪЛПИ 1Л.","PackCoeff":"1","ItemName":"ПЛОД.НАП.КАПИ ПРАСКОВА ПЪЛПИ 1Л.                                      ","Measure":"БР.","Quantity":"1.000","VendorPrice":"1.6700","ClientSurcharge":"0.00","ClientPrice":"1.95","PackDiscount":"0","ClientPriceBase":"1.63","Price":"1.95","DiscountValue":"0.00","DiscountType":"0","TotalBase":"1.63","VATRate":"20.00","TotalVAT":"0.32","Total":"1.95","IsCancelled":"не"},{"GID":"305303394","ParentGID":"302308052","SaleUniqueID":"DT652293-0006-0308052","UserGID":"6","CreatedDate":"08-06-21","CreatedTime":"17:29:55","SaleDate":"08-06-21","SaleTime":"17:30:36","Typed":"725","ItemGID":"346","BarCode":"725","BaseItemName":"ЗАХАР БУРГАСПАК 1КГ.","PackCoeff":"1","ItemName":"ЗАХАР БУРГАСПАК 1КГ.                                                  ","Measure":"БР.","Quantity":"1.000","VendorPrice":"1.2800","ClientSurcharge":"0.00","ClientPrice":"1.35","PackDiscount":"0","ClientPriceBase":"1.13","Price":"1.35","DiscountValue":"0.00","DiscountType":"0","TotalBase":"1.13","VATRate":"20.00","TotalVAT":"0.22","Total":"1.35","IsCancelled":"не"},{"GID":"305303396","ParentGID":"302308052","SaleUniqueID":"DT652293-0006-0308052","UserGID":"6","CreatedDate":"08-06-21","CreatedTime":"17:29:55","SaleDate":"08-06-21","SaleTime":"17:30:40","Typed":"3800090602460","ItemGID":"11757","BarCode":"3800090602460","BaseItemName":"САЛФЕТКИ СИСИ БЕЛИ","PackCoeff":"1","ItemName":"САЛФЕТКИ СИСИ БЕЛИ                                                    ","Measure":"БР.","Quantity":"1.000","VendorPrice":"0.5720","ClientSurcharge":"0.00","ClientPrice":"0.72","PackDiscount":"0","ClientPriceBase":"0.60","Price":"0.72","DiscountValue":"0.00","DiscountType":"0","TotalBase":"0.60","VATRate":"20.00","TotalVAT":"0.12","Total":"0.72","IsCancelled":"не"},{"GID":"305303398","ParentGID":"302308052","SaleUniqueID":"DT652293-0006-0308052","UserGID":"6","CreatedDate":"08-06-21","CreatedTime":"17:29:55","SaleDate":"08-06-21","SaleTime":"17:30:49","Typed":"8000700000005","ItemGID":"806","BarCode":"8000700000005","BaseItemName":"САПУН ДАФ","PackCoeff":"1","ItemName":"САПУН ДАФ                                                             ","Measure":"БР.","Quantity":"1.000","VendorPrice":"0.7783","ClientSurcharge":"0.00","ClientPrice":"0.92","PackDiscount":"0","ClientPriceBase":"0.77","Price":"0.92","DiscountValue":"0.00","DiscountType":"0","TotalBase":"0.77","VATRate":"20.00","TotalVAT":"0.15","Total":"0.92","IsCancelled":"не"},{"GID":"305303400","ParentGID":"302308052","SaleUniqueID":"DT652293-0006-0308052","UserGID":"6","CreatedDate":"08-06-21","CreatedTime":"17:29:55","SaleDate":"08-06-21","SaleTime":"17:30:52","Typed":"3800002310384","ItemGID":"100095194","BarCode":"3800002310384","BaseItemName":"МОКРИ КЪРПИ БЕБЕ БОЧКО 18БР","PackCoeff":"1","ItemName":"МОКРИ КЪРПИ БЕБЕ БОЧКО 18БР                                           ","Measure":"БР.","Quantity":"1.000","VendorPrice":"0.6190","ClientSurcharge":"0.00","ClientPrice":"0.75","PackDiscount":"0","ClientPriceBase":"0.63","Price":"0.75","DiscountValue":"0.00","DiscountType":"0","TotalBase":"0.63","VATRate":"20.00","TotalVAT":"0.12","Total":"0.75","IsCancelled":"не"},{"GID":"305303402","ParentGID":"302308052","SaleUniqueID":"DT652293-0006-0308052","UserGID":"6","CreatedDate":"08-06-21","CreatedTime":"17:29:55","SaleDate":"08-06-21","SaleTime":"17:30:56","Typed":"3800204650172","ItemGID":"347","BarCode":"3800204650172","BaseItemName":"ОЛИО БУРГАСПАК 1ЛИТЪР","PackCoeff":"1","ItemName":"ОЛИО БУРГАСПАК 1ЛИТЪР                                                 ","Measure":"БР.","Quantity":"1.000","VendorPrice":"2.9000","ClientSurcharge":"0.00","ClientPrice":"3.05","PackDiscount":"0","ClientPriceBase":"2.54","Price":"3.05","DiscountValue":"0.00","DiscountType":"0","TotalBase":"2.54","VATRate":"20.00","TotalVAT":"0.51","Total":"3.05","IsCancelled":"не"},{"GID":"305303404","ParentGID":"302308052","SaleUniqueID":"DT652293-0006-0308052","UserGID":"6","CreatedDate":"08-06-21","CreatedTime":"17:29:55","SaleDate":"08-06-21","SaleTime":"17:30:59","Typed":"5997312700696","ItemGID":"12012","BarCode":"5997312700696","BaseItemName":"ЧИО ЧИПС 65ГР.\/ВИДОВЕ","PackCoeff":"1","ItemName":"ЧИО ЧИПС 65ГР.\/ВИДОВЕ                                                 ","Measure":"БР.","Quantity":"1.000","VendorPrice":"1.0107","ClientSurcharge":"0.00","ClientPrice":"1.20","PackDiscount":"0","ClientPriceBase":"1.00","Price":"1.20","DiscountValue":"0.00","DiscountType":"0","TotalBase":"1.00","VATRate":"20.00","TotalVAT":"0.20","Total":"1.20","IsCancelled":"не"}],"Cancellations":[],"Reversals":[],"Payments":[{"GID":"302927572","ParentGID":"302308052","SaleUniqueID":"DT652293-0006-0308052","FiscalDeviceID":"DT652293","UserID":"6","CreatedDate":"08-06-21","CompletedDate":"08-06-21","Due":"21.84","PaymentDate":"08-06-21","PaymentType":"cash","PaymentBase":"18.33","PaymentVAT":"3.67","Payment":"22.00"},{"GID":"302927573","ParentGID":"302308052","SaleUniqueID":"DT652293-0006-0308052","FiscalDeviceID":"DT652293","UserID":"6","CreatedDate":"08-06-21","CompletedDate":"08-06-21","Due":"21.84","PaymentDate":"08-06-21","PaymentType":"returned","PaymentBase":"0.13","PaymentVAT":"0.03","Payment":"0.16"}]}