{"GID":"302817770","StoreID":"110","StoreName":"МАГАЗИН АНЕТ 4 бл.548","WorkstationID":"2","FiscalDeviceID":"DT938710","UserGID":"11","SaleID":"817770","SaleUniqueID":"DT938710-0011-0817770","ReceiptID":"298133","ClientGID":"1","ClientName":"КЛИЕНТ НА МАГАЗИН АНЕТ 4","ClientTaxNumberType":"0","ClientTaxNumber":"","ClientAddress":"","ClientReceiver":"","ClientBuyer":"","ClientVIPStatus":"","ClientSurcharge":"0.00","InvoiceID":"","InvoiceDate":"","CreatedDate":"27-10-23","CreatedTime":"14:23:14","CompletedDate":"27-10-23","CompletedTime":"14:24:05","TotalBase":"0.00","Discount":"0.00","TotalVAT":"0.00","Due":"26.74","CashPayment":"30.00","VoucherPayment":"0.00","CardPayment":"0.00","Returned":"3.26","Stage":"приключена","Details":[{"GID":"310428182","ParentGID":"302817770","SaleUniqueID":"DT938710-0011-0817770","UserGID":"11","CreatedDate":"27-10-23","CreatedTime":"14:23:14","SaleDate":"27-10-23","SaleTime":"14:23:14","Typed":"3800024026409","ItemGID":"9369","BarCode":"3800024026409","BaseItemName":"ТОАЛЕТНА ХАРТИЯ МИЛДЕ 8 БР.","PackCoeff":"1","ItemName":"ТОАЛЕТНА ХАРТИЯ МИЛДЕ 8 БР.                                           ","Measure":"БР.","Quantity":"1.000","VendorPrice":"5.2700","ClientSurcharge":"0.00","ClientPrice":"6.35","PackDiscount":"0","ClientPriceBase":"5.29","Price":"6.35","DiscountValue":"0.00","DiscountType":"0","TotalBase":"5.29","VATRate":"20.00","TotalVAT":"1.06","Total":"6.35","IsCancelled":"не"},{"GID":"310428184","ParentGID":"302817770","SaleUniqueID":"DT938710-0011-0817770","UserGID":"11","CreatedDate":"27-10-23","CreatedTime":"14:23:14","SaleDate":"27-10-23","SaleTime":"14:23:19","Typed":"3800748051213","ItemGID":"100594752","BarCode":"3800748051213","BaseItemName":"ПМ ВЕРЕЯ ЧУДНО 1.7% 1Л.","PackCoeff":"1","ItemName":"ПМ ВЕРЕЯ ЧУДНО 1.7% 1Л.                                               ","Measure":"БР.","Quantity":"1.000","VendorPrice":"2.6300","ClientSurcharge":"0.00","ClientPrice":"3.09","PackDiscount":"0","ClientPriceBase":"2.58","Price":"3.09","DiscountValue":"0.00","DiscountType":"0","TotalBase":"2.58","VATRate":"20.00","TotalVAT":"0.51","Total":"3.09","IsCancelled":"не"},{"GID":"310428186","ParentGID":"302817770","SaleUniqueID":"DT938710-0011-0817770","UserGID":"11","CreatedDate":"27-10-23","CreatedTime":"14:23:14","SaleDate":"27-10-23","SaleTime":"14:23:28","Typed":"3*3800052319122","ItemGID":"5544","BarCode":"3800052319122","BaseItemName":"БИРА СТАРОПРАМЕН КЕН 0.500Л.","PackCoeff":"1","ItemName":"БИРА СТАРОПРАМЕН КЕН 0.500Л.                                          ","Measure":"БР.","Quantity":"3.000","VendorPrice":"1.4600","ClientSurcharge":"0.00","ClientPrice":"1.59","PackDiscount":"0","ClientPriceBase":"1.33","Price":"1.59","DiscountValue":"0.00","DiscountType":"0","TotalBase":"3.98","VATRate":"20.00","TotalVAT":"0.79","Total":"4.77","IsCancelled":"не"},{"GID":"310428188","ParentGID":"302817770","SaleUniqueID":"DT938710-0011-0817770","UserGID":"11","CreatedDate":"27-10-23","CreatedTime":"14:23:14","SaleDate":"27-10-23","SaleTime":"14:23:34","Typed":"2*3800207820930","ItemGID":"100738698","BarCode":"3800207820930","BaseItemName":"КИСЕЛО МЛЯКО БОЖЕНЦИ 3.6% 400ГР.БДС","PackCoeff":"1","ItemName":"КИСЕЛО МЛЯКО БОЖЕНЦИ 3.6% 400ГР.БДС                                   ","Measure":"БР.","Quantity":"2.000","VendorPrice":"1.1905","ClientSurcharge":"0.00","ClientPrice":"1.39","PackDiscount":"0","ClientPriceBase":"1.16","Price":"1.39","DiscountValue":"0.00","DiscountType":"0","TotalBase":"2.32","VATRate":"20.00","TotalVAT":"0.46","Total":"2.78","IsCancelled":"не"},{"GID":"310428190","ParentGID":"302817770","SaleUniqueID":"DT938710-0011-0817770","UserGID":"11","CreatedDate":"27-10-23","CreatedTime":"14:23:14","SaleDate":"27-10-23","SaleTime":"14:23:37","Typed":"1900141003986","ItemGID":"14799","BarCode":"141","BaseItemName":"КРАВЕ СИРЕНЕ СИТОВО - МАНДРА С.СИТОВО","PackCoeff":"1","ItemName":"КРАВЕ СИРЕНЕ СИТОВО - МАНДРА С.СИТОВО                                 ","Measure":"КГ.","Quantity":"0.398","VendorPrice":"10.7310","ClientSurcharge":"0.00","ClientPrice":"12.59","PackDiscount":"0","ClientPriceBase":"10.49","Price":"12.59","DiscountValue":"0.00","DiscountType":"0","TotalBase":"4.18","VATRate":"20.00","TotalVAT":"0.83","Total":"5.01","IsCancelled":"не"},{"GID":"310428192","ParentGID":"302817770","SaleUniqueID":"DT938710-0011-0817770","UserGID":"11","CreatedDate":"27-10-23","CreatedTime":"14:23:14","SaleDate":"27-10-23","SaleTime":"14:23:40","Typed":"3800024026591","ItemGID":"14176","BarCode":"3800024026591","BaseItemName":"КУХ.РОЛКА ЕМЕКА 2-КА","PackCoeff":"1","ItemName":"КУХ.РОЛКА ЕМЕКА 2-КА                                                  ","Measure":"БР.","Quantity":"1.000","VendorPrice":"2.3280","ClientSurcharge":"0.00","ClientPrice":"3.35","PackDiscount":"0","ClientPriceBase":"2.79","Price":"3.35","DiscountValue":"0.00","DiscountType":"0","TotalBase":"2.79","VATRate":"20.00","TotalVAT":"0.56","Total":"3.35","IsCancelled":"не"},{"GID":"310428194","ParentGID":"302817770","SaleUniqueID":"DT938710-0011-0817770","UserGID":"11","CreatedDate":"27-10-23","CreatedTime":"14:23:14","SaleDate":"27-10-23","SaleTime":"14:23:44","Typed":"3800207820930","ItemGID":"100738698","BarCode":"3800207820930","BaseItemName":"КИСЕЛО МЛЯКО БОЖЕНЦИ 3.6% 400ГР.БДС","PackCoeff":"1","ItemName":"КИСЕЛО МЛЯКО БОЖЕНЦИ 3.6% 400ГР.БДС                                   ","Measure":"БР.","Quantity":"1.000","VendorPrice":"1.1905","ClientSurcharge":"0.00","ClientPrice":"1.39","PackDiscount":"0","ClientPriceBase":"1.16","Price":"1.39","DiscountValue":"0.00","DiscountType":"0","TotalBase":"1.16","VATRate":"20.00","TotalVAT":"0.23","Total":"1.39","IsCancelled":"не"}],"Cancellations":[],"Reversals":[],"Payments":[{"GID":"303916214","ParentGID":"302817770","SaleUniqueID":"DT938710-0011-0817770","FiscalDeviceID":"DT938710","UserID":"11","CreatedDate":"27-10-23","CompletedDate":"27-10-23","Due":"26.74","PaymentDate":"27-10-23","PaymentType":"cash","PaymentBase":"25.00","PaymentVAT":"5.00","Payment":"30.00"},{"GID":"303916215","ParentGID":"302817770","SaleUniqueID":"DT938710-0011-0817770","FiscalDeviceID":"DT938710","UserID":"11","CreatedDate":"27-10-23","CompletedDate":"27-10-23","Due":"26.74","PaymentDate":"27-10-23","PaymentType":"returned","PaymentBase":"2.72","PaymentVAT":"0.54","Payment":"3.26"}]}