{"GID":"302307617","StoreID":"110","StoreName":"МАГАЗИН АНЕТ 4 бл.548","WorkstationID":"2","FiscalDeviceID":"DT652293","UserGID":"3","SaleID":"307617","SaleUniqueID":"DT652293-0003-0307617","ReceiptID":"755936","ClientGID":"1","ClientName":"КЛИЕНТ НА МАГАЗИН АНЕТ 4","ClientTaxNumberType":"0","ClientTaxNumber":"","ClientAddress":"","ClientReceiver":"","ClientBuyer":"","ClientVIPStatus":"","ClientSurcharge":"0.00","InvoiceID":"","InvoiceDate":"","CreatedDate":"07-06-21","CreatedTime":"17:49:13","CompletedDate":"07-06-21","CompletedTime":"17:49:52","TotalBase":"0.00","Discount":"0.00","TotalVAT":"0.00","Due":"15.09","CashPayment":"20.00","VoucherPayment":"0.00","CardPayment":"0.00","Returned":"4.91","Stage":"приключена","Details":[{"GID":"305299002","ParentGID":"302307617","SaleUniqueID":"DT652293-0003-0307617","UserGID":"3","CreatedDate":"07-06-21","CreatedTime":"17:49:13","SaleDate":"07-06-21","SaleTime":"17:49:13","Typed":"5449000301017","ItemGID":"100793732","BarCode":"5449000301017","BaseItemName":"ГАЗ.НАП.ШВЕПС ТОНИК РОЗОВ 1.25Л.","PackCoeff":"1","ItemName":"ГАЗ.НАП.ШВЕПС ТОНИК РОЗОВ 1.25Л.                                      ","Measure":"БР.","Quantity":"1.000","VendorPrice":"1.6600","ClientSurcharge":"0.00","ClientPrice":"1.95","PackDiscount":"0","ClientPriceBase":"1.63","Price":"1.95","DiscountValue":"0.00","DiscountType":"0","TotalBase":"1.63","VATRate":"20.00","TotalVAT":"0.32","Total":"1.95","IsCancelled":"не"},{"GID":"305299004","ParentGID":"302307617","SaleUniqueID":"DT652293-0003-0307617","UserGID":"3","CreatedDate":"07-06-21","CreatedTime":"17:49:13","SaleDate":"07-06-21","SaleTime":"17:49:16","Typed":"5201360521005","ItemGID":"100111176","BarCode":"5201360521005","BaseItemName":"КРОАСАН ЧИПИКАО 60ГР.","PackCoeff":"1","ItemName":"КРОАСАН ЧИПИКАО 60ГР.                                                 ","Measure":"БР.","Quantity":"1.000","VendorPrice":"0.6550","ClientSurcharge":"0.00","ClientPrice":"0.80","PackDiscount":"0","ClientPriceBase":"0.67","Price":"0.80","DiscountValue":"0.00","DiscountType":"0","TotalBase":"0.67","VATRate":"20.00","TotalVAT":"0.13","Total":"0.80","IsCancelled":"не"},{"GID":"305299006","ParentGID":"302307617","SaleUniqueID":"DT652293-0003-0307617","UserGID":"3","CreatedDate":"07-06-21","CreatedTime":"17:49:13","SaleDate":"07-06-21","SaleTime":"17:49:19","Typed":"5201360521005","ItemGID":"100111176","BarCode":"5201360521005","BaseItemName":"КРОАСАН ЧИПИКАО 60ГР.","PackCoeff":"1","ItemName":"КРОАСАН ЧИПИКАО 60ГР.                                                 ","Measure":"БР.","Quantity":"1.000","VendorPrice":"0.6550","ClientSurcharge":"0.00","ClientPrice":"0.80","PackDiscount":"0","ClientPriceBase":"0.67","Price":"0.80","DiscountValue":"0.00","DiscountType":"0","TotalBase":"0.67","VATRate":"20.00","TotalVAT":"0.13","Total":"0.80","IsCancelled":"не"},{"GID":"305299008","ParentGID":"302307617","SaleUniqueID":"DT652293-0003-0307617","UserGID":"3","CreatedDate":"07-06-21","CreatedTime":"17:49:13","SaleDate":"07-06-21","SaleTime":"17:49:21","Typed":"80710196","ItemGID":"100137911","BarCode":"80710196","BaseItemName":"ШОК.ЯЙЦА ДИСНИ\/ВИДОВЕ","PackCoeff":"1","ItemName":"ШОК.ЯЙЦА ДИСНИ\/ВИДОВЕ                                                 ","Measure":"БР.","Quantity":"1.000","VendorPrice":"1.0250","ClientSurcharge":"0.00","ClientPrice":"1.25","PackDiscount":"0","ClientPriceBase":"1.04","Price":"1.25","DiscountValue":"0.00","DiscountType":"0","TotalBase":"1.04","VATRate":"20.00","TotalVAT":"0.21","Total":"1.25","IsCancelled":"не"},{"GID":"305299010","ParentGID":"302307617","SaleUniqueID":"DT652293-0003-0307617","UserGID":"3","CreatedDate":"07-06-21","CreatedTime":"17:49:13","SaleDate":"07-06-21","SaleTime":"17:49:26","Typed":"лед 1 кг","ItemGID":"100349681","BarCode":"38025440","BaseItemName":"ЛЕД НА КУБЧЕТА 1КГ.","PackCoeff":"1","ItemName":"ЛЕД НА КУБЧЕТА 1КГ.                                                   ","Measure":"БР.","Quantity":"1.000","VendorPrice":"0.9000","ClientSurcharge":"0.00","ClientPrice":"1.10","PackDiscount":"0","ClientPriceBase":"0.92","Price":"1.10","DiscountValue":"0.00","DiscountType":"0","TotalBase":"0.92","VATRate":"20.00","TotalVAT":"0.18","Total":"1.10","IsCancelled":"не"},{"GID":"305299012","ParentGID":"302307617","SaleUniqueID":"DT652293-0003-0307617","UserGID":"3","CreatedDate":"07-06-21","CreatedTime":"17:49:13","SaleDate":"07-06-21","SaleTime":"17:49:28","Typed":"3800216170026","ItemGID":"100192359","BarCode":"3800216170026","BaseItemName":"РИБА ПЕРЛА 180ГР.\/ЕКОПРОМ","PackCoeff":"1","ItemName":"РИБА ПЕРЛА 180ГР.\/ЕКОПРОМ                                             ","Measure":"БР.","Quantity":"1.000","VendorPrice":"1.5500","ClientSurcharge":"0.00","ClientPrice":"1.85","PackDiscount":"0","ClientPriceBase":"1.54","Price":"1.85","DiscountValue":"0.00","DiscountType":"0","TotalBase":"1.54","VATRate":"20.00","TotalVAT":"0.31","Total":"1.85","IsCancelled":"не"},{"GID":"305299014","ParentGID":"302307617","SaleUniqueID":"DT652293-0003-0307617","UserGID":"3","CreatedDate":"07-06-21","CreatedTime":"17:49:13","SaleDate":"07-06-21","SaleTime":"17:49:33","Typed":"3800008903313","ItemGID":"12624","BarCode":"3800008903313","BaseItemName":"ДЖИН 0.5 САВОЙ КЛУБ","PackCoeff":"1","ItemName":"ДЖИН 0.5 САВОЙ КЛУБ                                                   ","Measure":"БР.","Quantity":"1.000","VendorPrice":"5.2528","ClientSurcharge":"0.00","ClientPrice":"6.05","PackDiscount":"0","ClientPriceBase":"5.04","Price":"6.05","DiscountValue":"0.00","DiscountType":"0","TotalBase":"5.04","VATRate":"20.00","TotalVAT":"1.01","Total":"6.05","IsCancelled":"не"},{"GID":"305299016","ParentGID":"302307617","SaleUniqueID":"DT652293-0003-0307617","UserGID":"3","CreatedDate":"07-06-21","CreatedTime":"17:49:13","SaleDate":"07-06-21","SaleTime":"17:49:35","Typed":"5201360117239","ItemGID":"134","BarCode":"5201360117239","BaseItemName":"ТЕЧ.ШОКОЛАД ФИНЕТИ 190ГР.","PackCoeff":"1","ItemName":"ТЕЧ.ШОКОЛАД ФИНЕТИ 190ГР.                                             ","Measure":"БР.","Quantity":"1.000","VendorPrice":"1.0040","ClientSurcharge":"0.00","ClientPrice":"1.29","PackDiscount":"0","ClientPriceBase":"1.08","Price":"1.29","DiscountValue":"0.00","DiscountType":"0","TotalBase":"1.08","VATRate":"20.00","TotalVAT":"0.21","Total":"1.29","IsCancelled":"не"}],"Cancellations":[],"Reversals":[],"Payments":[{"GID":"302926717","ParentGID":"302307617","SaleUniqueID":"DT652293-0003-0307617","FiscalDeviceID":"DT652293","UserID":"3","CreatedDate":"07-06-21","CompletedDate":"07-06-21","Due":"15.09","PaymentDate":"07-06-21","PaymentType":"cash","PaymentBase":"16.67","PaymentVAT":"3.33","Payment":"20.00"},{"GID":"302926718","ParentGID":"302307617","SaleUniqueID":"DT652293-0003-0307617","FiscalDeviceID":"DT652293","UserID":"3","CreatedDate":"07-06-21","CompletedDate":"07-06-21","Due":"15.09","PaymentDate":"07-06-21","PaymentType":"returned","PaymentBase":"4.09","PaymentVAT":"0.82","Payment":"4.91"}]}