{"GID":"302361269","StoreID":"110","StoreName":"МАГАЗИН АНЕТ 4 бл.548","WorkstationID":"2","FiscalDeviceID":"DT652293","UserGID":"8","SaleID":"361269","SaleUniqueID":"DT652293-0008-0361269","ReceiptID":"810346","ClientGID":"1","ClientName":"КЛИЕНТ НА МАГАЗИН АНЕТ 4","ClientTaxNumberType":"0","ClientTaxNumber":"","ClientAddress":"","ClientReceiver":"","ClientBuyer":"","ClientVIPStatus":"","ClientSurcharge":"0.00","InvoiceID":"","InvoiceDate":"","CreatedDate":"14-09-21","CreatedTime":"15:55:36","CompletedDate":"14-09-21","CompletedTime":"15:55:45","TotalBase":"0.00","Discount":"0.00","TotalVAT":"0.00","Due":"7.44","CashPayment":"50.00","VoucherPayment":"0.00","CardPayment":"0.00","Returned":"42.56","Stage":"приключена","Details":[{"GID":"305835528","ParentGID":"302361269","SaleUniqueID":"DT652293-0008-0361269","UserGID":"8","CreatedDate":"14-09-21","CreatedTime":"15:55:36","SaleDate":"14-09-21","SaleTime":"15:55:36","Typed":"9002859062131","ItemGID":"100608871","BarCode":"9002859062131","BaseItemName":"ШОК.БОНБОНИ АСОРТИ 400ГР.\/ВИДОВЕ","PackCoeff":"1","ItemName":"ШОК.БОНБОНИ АСОРТИ 400ГР.\/ВИДОВЕ                                      ","Measure":"БР.","Quantity":"1.000","VendorPrice":"3.4200","ClientSurcharge":"0.00","ClientPrice":"3.99","PackDiscount":"0","ClientPriceBase":"3.33","Price":"3.99","DiscountValue":"0.00","DiscountType":"0","TotalBase":"3.33","VATRate":"20.00","TotalVAT":"0.66","Total":"3.99","IsCancelled":"не"},{"GID":"305835530","ParentGID":"302361269","SaleUniqueID":"DT652293-0008-0361269","UserGID":"8","CreatedDate":"14-09-21","CreatedTime":"15:55:36","SaleDate":"14-09-21","SaleTime":"15:55:38","Typed":"5941000025431","ItemGID":"17409","BarCode":"5941000025431","BaseItemName":"ЧИПС РАФЪЛС 260ГР.ВИДОВЕ","PackCoeff":"1","ItemName":"ЧИПС РАФЪЛС 260ГР.ВИДОВЕ                                              ","Measure":"БР.","Quantity":"1.000","VendorPrice":"2.9280","ClientSurcharge":"0.00","ClientPrice":"3.45","PackDiscount":"0","ClientPriceBase":"2.88","Price":"3.45","DiscountValue":"0.00","DiscountType":"0","TotalBase":"2.88","VATRate":"20.00","TotalVAT":"0.57","Total":"3.45","IsCancelled":"не"}],"Cancellations":[],"Reversals":[],"Payments":[{"GID":"303030975","ParentGID":"302361269","SaleUniqueID":"DT652293-0008-0361269","FiscalDeviceID":"DT652293","UserID":"8","CreatedDate":"14-09-21","CompletedDate":"14-09-21","Due":"7.44","PaymentDate":"14-09-21","PaymentType":"cash","PaymentBase":"41.67","PaymentVAT":"8.33","Payment":"50.00"},{"GID":"303030976","ParentGID":"302361269","SaleUniqueID":"DT652293-0008-0361269","FiscalDeviceID":"DT652293","UserID":"8","CreatedDate":"14-09-21","CompletedDate":"14-09-21","Due":"7.44","PaymentDate":"14-09-21","PaymentType":"returned","PaymentBase":"35.47","PaymentVAT":"7.09","Payment":"42.56"}]}