{"GID":"302764581","StoreID":"110","StoreName":"МАГАЗИН АНЕТ 4 бл.548","WorkstationID":"2","FiscalDeviceID":"DT938710","UserGID":"3","SaleID":"764581","SaleUniqueID":"DT938710-0003-0764581","ReceiptID":"244167","ClientGID":"1","ClientName":"КЛИЕНТ НА МАГАЗИН АНЕТ 4","ClientTaxNumberType":"0","ClientTaxNumber":"","ClientAddress":"","ClientReceiver":"","ClientBuyer":"","ClientVIPStatus":"","ClientSurcharge":"0.00","InvoiceID":"","InvoiceDate":"","CreatedDate":"07-08-23","CreatedTime":"18:29:07","CompletedDate":"07-08-23","CompletedTime":"18:29:33","TotalBase":"0.00","Discount":"0.00","TotalVAT":"0.00","Due":"14.67","CashPayment":"20.00","VoucherPayment":"0.00","CardPayment":"0.00","Returned":"5.33","Stage":"приключена","Details":[{"GID":"309910530","ParentGID":"302764581","SaleUniqueID":"DT938710-0003-0764581","UserGID":"3","CreatedDate":"07-08-23","CreatedTime":"18:29:07","SaleDate":"07-08-23","SaleTime":"18:29:07","Typed":"3*3800115377106","ItemGID":"100049862","BarCode":"3800115377106","BaseItemName":"СЛАДОЛЕД БОМБАСТИК 65ГР. ИЗИДА","PackCoeff":"1","ItemName":"СЛАДОЛЕД БОМБАСТИК 65ГР. ИЗИДА                                        ","Measure":"БР.","Quantity":"3.000","VendorPrice":"1.1000","ClientSurcharge":"0.00","ClientPrice":"1.10","PackDiscount":"0","ClientPriceBase":"0.92","Price":"1.10","DiscountValue":"0.00","DiscountType":"0","TotalBase":"2.75","VATRate":"20.00","TotalVAT":"0.55","Total":"3.30","IsCancelled":"не"},{"GID":"309910532","ParentGID":"302764581","SaleUniqueID":"DT938710-0003-0764581","UserGID":"3","CreatedDate":"07-08-23","CreatedTime":"18:29:07","SaleDate":"07-08-23","SaleTime":"18:29:10","Typed":"3800205450177","ItemGID":"100504003","BarCode":"3800205450177","BaseItemName":"ХЛЯБ МУЛТИСЕРИАЛ ДИАМАНТ 400ГР.","PackCoeff":"1","ItemName":"ХЛЯБ МУЛТИСЕРИАЛ ДИАМАНТ 400ГР.                                       ","Measure":"БР.","Quantity":"1.000","VendorPrice":"1.5750","ClientSurcharge":"0.00","ClientPrice":"1.82","PackDiscount":"0","ClientPriceBase":"1.82","Price":"1.82","DiscountValue":"0.00","DiscountType":"0","TotalBase":"1.82","VATRate":"0.00","TotalVAT":"0.00","Total":"1.82","IsCancelled":"не"},{"GID":"309910534","ParentGID":"302764581","SaleUniqueID":"DT938710-0003-0764581","UserGID":"3","CreatedDate":"07-08-23","CreatedTime":"18:29:07","SaleDate":"07-08-23","SaleTime":"18:29:12","Typed":"4740056072076","ItemGID":"100241853","BarCode":"4740056072076","BaseItemName":"ПАНИРАНИ ПРЪСТЧЕТА ОТ КАЛМАРИ 250ГР. КОЛ","PackCoeff":"1","ItemName":"ПАНИРАНИ ПРЪСТЧЕТА ОТ КАЛМАРИ 250ГР. КОЛ                              ","Measure":"БР.","Quantity":"1.000","VendorPrice":"3.8016","ClientSurcharge":"0.00","ClientPrice":"4.55","PackDiscount":"0","ClientPriceBase":"3.79","Price":"4.55","DiscountValue":"0.00","DiscountType":"0","TotalBase":"3.79","VATRate":"20.00","TotalVAT":"0.76","Total":"4.55","IsCancelled":"не"},{"GID":"309910536","ParentGID":"302764581","SaleUniqueID":"DT938710-0003-0764581","UserGID":"3","CreatedDate":"07-08-23","CreatedTime":"18:29:07","SaleDate":"07-08-23","SaleTime":"18:29:23","Typed":"3800216128850","ItemGID":"100967474","BarCode":"3800216128850","BaseItemName":"ЦИГАРИ ФИЛИП МОРИС ХS РОЗОВ","PackCoeff":"1","ItemName":"ЦИГАРИ ФИЛИП МОРИС ХS РОЗОВ                                           ","Measure":"БР.","Quantity":"1.000","VendorPrice":"4.7436","ClientSurcharge":"0.00","ClientPrice":"5.00","PackDiscount":"0","ClientPriceBase":"4.17","Price":"5.00","DiscountValue":"0.00","DiscountType":"0","TotalBase":"4.17","VATRate":"20.00","TotalVAT":"0.83","Total":"5.00","IsCancelled":"не"}],"Cancellations":[],"Reversals":[],"Payments":[{"GID":"303812665","ParentGID":"302764581","SaleUniqueID":"DT938710-0003-0764581","FiscalDeviceID":"DT938710","UserID":"3","CreatedDate":"07-08-23","CompletedDate":"07-08-23","Due":"14.67","PaymentDate":"07-08-23","PaymentType":"cash","PaymentBase":"16.67","PaymentVAT":"3.33","Payment":"20.00"},{"GID":"303812666","ParentGID":"302764581","SaleUniqueID":"DT938710-0003-0764581","FiscalDeviceID":"DT938710","UserID":"3","CreatedDate":"07-08-23","CompletedDate":"07-08-23","Due":"14.67","PaymentDate":"07-08-23","PaymentType":"returned","PaymentBase":"4.44","PaymentVAT":"0.89","Payment":"5.33"}]}