{"GID":"302400686","StoreID":"110","StoreName":"МАГАЗИН АНЕТ 4 бл.548","WorkstationID":"2","FiscalDeviceID":"DT652293","UserGID":"3","SaleID":"400686","SaleUniqueID":"DT652293-0003-0400686","ReceiptID":"850403","ClientGID":"1","ClientName":"КЛИЕНТ НА МАГАЗИН АНЕТ 4","ClientTaxNumberType":"0","ClientTaxNumber":"","ClientAddress":"","ClientReceiver":"","ClientBuyer":"","ClientVIPStatus":"","ClientSurcharge":"0.00","InvoiceID":"","InvoiceDate":"","CreatedDate":"27-11-21","CreatedTime":"18:01:06","CompletedDate":"27-11-21","CompletedTime":"18:01:59","TotalBase":"0.00","Discount":"0.00","TotalVAT":"0.00","Due":"10.45","CashPayment":"10.45","VoucherPayment":"0.00","CardPayment":"0.00","Returned":"0.00","Stage":"приключена","Details":[{"GID":"306262506","ParentGID":"302400686","SaleUniqueID":"DT652293-0003-0400686","UserGID":"3","CreatedDate":"27-11-21","CreatedTime":"18:01:06","SaleDate":"27-11-21","SaleTime":"18:01:06","Typed":"3800151100355","ItemGID":"100084423","BarCode":"3800151100355","BaseItemName":"СЛЪНЧОГЛЕД СОЛЕН\/ПОДПРАВКА 80ГР","PackCoeff":"1","ItemName":"СЛЪНЧОГЛЕД СОЛЕН\/ПОДПРАВКА 80ГР                                       ","Measure":"БР.","Quantity":"1.000","VendorPrice":"0.8400","ClientSurcharge":"0.00","ClientPrice":"1.00","PackDiscount":"0","ClientPriceBase":"0.83","Price":"1.00","DiscountValue":"0.00","DiscountType":"0","TotalBase":"0.83","VATRate":"20.00","TotalVAT":"0.17","Total":"1.00","IsCancelled":"не"},{"GID":"306262508","ParentGID":"302400686","SaleUniqueID":"DT652293-0003-0400686","UserGID":"3","CreatedDate":"27-11-21","CreatedTime":"18:01:06","SaleDate":"27-11-21","SaleTime":"18:01:09","Typed":"3800216291165","ItemGID":"100076335","BarCode":"3800216291165","BaseItemName":"КАРНАЧЕ ЧЕРНЕВ 250ГР.","PackCoeff":"1","ItemName":"КАРНАЧЕ ЧЕРНЕВ 250ГР.                                                 ","Measure":"БР.","Quantity":"1.000","VendorPrice":"1.5500","ClientSurcharge":"0.00","ClientPrice":"1.85","PackDiscount":"0","ClientPriceBase":"1.54","Price":"1.85","DiscountValue":"0.00","DiscountType":"0","TotalBase":"1.54","VATRate":"20.00","TotalVAT":"0.31","Total":"1.85","IsCancelled":"не"},{"GID":"306262510","ParentGID":"302400686","SaleUniqueID":"DT652293-0003-0400686","UserGID":"3","CreatedDate":"27-11-21","CreatedTime":"18:01:06","SaleDate":"27-11-21","SaleTime":"18:01:12","Typed":"3800216291165","ItemGID":"100076335","BarCode":"3800216291165","BaseItemName":"КАРНАЧЕ ЧЕРНЕВ 250ГР.","PackCoeff":"1","ItemName":"КАРНАЧЕ ЧЕРНЕВ 250ГР.                                                 ","Measure":"БР.","Quantity":"1.000","VendorPrice":"1.5500","ClientSurcharge":"0.00","ClientPrice":"1.85","PackDiscount":"0","ClientPriceBase":"1.54","Price":"1.85","DiscountValue":"0.00","DiscountType":"0","TotalBase":"1.54","VATRate":"20.00","TotalVAT":"0.31","Total":"1.85","IsCancelled":"не"},{"GID":"306262512","ParentGID":"302400686","SaleUniqueID":"DT652293-0003-0400686","UserGID":"3","CreatedDate":"27-11-21","CreatedTime":"18:01:06","SaleDate":"27-11-21","SaleTime":"18:01:16","Typed":"3800206523221","ItemGID":"11106","BarCode":"3800206523221","BaseItemName":"ТХК ФЕРМАТА 270ГР.\/ВИДОВЕ","PackCoeff":"1","ItemName":"ТХК ФЕРМАТА 270ГР.\/ВИДОВЕ                                             ","Measure":"БР.","Quantity":"1.000","VendorPrice":"0.7950","ClientSurcharge":"0.00","ClientPrice":"0.95","PackDiscount":"0","ClientPriceBase":"0.79","Price":"0.95","DiscountValue":"0.00","DiscountType":"0","TotalBase":"0.79","VATRate":"20.00","TotalVAT":"0.16","Total":"0.95","IsCancelled":"не"},{"GID":"306262514","ParentGID":"302400686","SaleUniqueID":"DT652293-0003-0400686","UserGID":"3","CreatedDate":"27-11-21","CreatedTime":"18:01:06","SaleDate":"27-11-21","SaleTime":"18:01:31","Typed":"3800203781303","ItemGID":"100567055","BarCode":"3800203781303","BaseItemName":"СУХА ПАСТА ПЕРУН 60ГР.","PackCoeff":"1","ItemName":"СУХА ПАСТА ПЕРУН 60ГР.                                                ","Measure":"БР.","Quantity":"1.000","VendorPrice":"0.4200","ClientSurcharge":"0.00","ClientPrice":"0.50","PackDiscount":"0","ClientPriceBase":"0.42","Price":"0.50","DiscountValue":"0.00","DiscountType":"0","TotalBase":"0.42","VATRate":"20.00","TotalVAT":"0.08","Total":"0.50","IsCancelled":"не"},{"GID":"306262516","ParentGID":"302400686","SaleUniqueID":"DT652293-0003-0400686","UserGID":"3","CreatedDate":"27-11-21","CreatedTime":"18:01:06","SaleDate":"27-11-21","SaleTime":"18:01:33","Typed":"3800098100043","ItemGID":"3878","BarCode":"3800098100043","BaseItemName":"МАРГАРИН ТОММИ 250ГР.","PackCoeff":"1","ItemName":"МАРГАРИН ТОММИ 250ГР.                                                 ","Measure":"БР.","Quantity":"1.000","VendorPrice":"0.8760","ClientSurcharge":"0.00","ClientPrice":"1.05","PackDiscount":"0","ClientPriceBase":"0.88","Price":"1.05","DiscountValue":"0.00","DiscountType":"0","TotalBase":"0.88","VATRate":"20.00","TotalVAT":"0.17","Total":"1.05","IsCancelled":"не"},{"GID":"306262518","ParentGID":"302400686","SaleUniqueID":"DT652293-0003-0400686","UserGID":"3","CreatedDate":"27-11-21","CreatedTime":"18:01:06","SaleDate":"27-11-21","SaleTime":"18:01:36","Typed":"3800207280048","ItemGID":"100008741","BarCode":"3800207280048","BaseItemName":"ГАЗИРАНА НАПИТКА \"ЕЛИТ\" 2Л.ВИДОВЕ","PackCoeff":"1","ItemName":"ГАЗИРАНА НАПИТКА \"ЕЛИТ\" 2Л.ВИДОВЕ                                     ","Measure":"БР.","Quantity":"1.000","VendorPrice":"0.5500","ClientSurcharge":"0.00","ClientPrice":"0.65","PackDiscount":"0","ClientPriceBase":"0.54","Price":"0.65","DiscountValue":"0.00","DiscountType":"0","TotalBase":"0.54","VATRate":"20.00","TotalVAT":"0.11","Total":"0.65","IsCancelled":"не"},{"GID":"306262520","ParentGID":"302400686","SaleUniqueID":"DT652293-0003-0400686","UserGID":"3","CreatedDate":"27-11-21","CreatedTime":"18:01:06","SaleDate":"27-11-21","SaleTime":"18:01:40","Typed":"3*3800102719582","ItemGID":"8633","BarCode":"3800102719582","BaseItemName":"ШОК.ВАФЛИ ЧЕРВЕН БОРОВЕЦ 30ГР.","PackCoeff":"1","ItemName":"ШОК.ВАФЛИ ЧЕРВЕН БОРОВЕЦ 30ГР.                                        ","Measure":"БР.","Quantity":"3.000","VendorPrice":"0.1840","ClientSurcharge":"0.00","ClientPrice":"0.22","PackDiscount":"0","ClientPriceBase":"0.18","Price":"0.22","DiscountValue":"0.00","DiscountType":"0","TotalBase":"0.55","VATRate":"20.00","TotalVAT":"0.11","Total":"0.66","IsCancelled":"не"},{"GID":"306262522","ParentGID":"302400686","SaleUniqueID":"DT652293-0003-0400686","UserGID":"3","CreatedDate":"27-11-21","CreatedTime":"18:01:06","SaleDate":"27-11-21","SaleTime":"18:01:43","Typed":"3800500200361","ItemGID":"100333622","BarCode":"3800500200361","BaseItemName":"КИСЕЛО МЛЯКО ДЕБЕЛТ 3.6% 400ГР.","PackCoeff":"1","ItemName":"КИСЕЛО МЛЯКО ДЕБЕЛТ 3.6% 400ГР.                                       ","Measure":"БР.","Quantity":"1.000","VendorPrice":"0.7350","ClientSurcharge":"0.00","ClientPrice":"0.85","PackDiscount":"0","ClientPriceBase":"0.71","Price":"0.85","DiscountValue":"0.00","DiscountType":"0","TotalBase":"0.71","VATRate":"20.00","TotalVAT":"0.14","Total":"0.85","IsCancelled":"не"},{"GID":"306262524","ParentGID":"302400686","SaleUniqueID":"DT652293-0003-0400686","UserGID":"3","CreatedDate":"27-11-21","CreatedTime":"18:01:06","SaleDate":"27-11-21","SaleTime":"18:01:44","Typed":"3800024310058","ItemGID":"11135","BarCode":"3800024310058","BaseItemName":"ЛОТО НАТУРАЛ 45ГР.","PackCoeff":"1","ItemName":"ЛОТО НАТУРАЛ 45ГР.                                                    ","Measure":"БР.","Quantity":"1.000","VendorPrice":"0.3229","ClientSurcharge":"0.00","ClientPrice":"0.39","PackDiscount":"0","ClientPriceBase":"0.33","Price":"0.39","DiscountValue":"0.00","DiscountType":"0","TotalBase":"0.33","VATRate":"20.00","TotalVAT":"0.06","Total":"0.39","IsCancelled":"не"},{"GID":"306262526","ParentGID":"302400686","SaleUniqueID":"DT652293-0003-0400686","UserGID":"3","CreatedDate":"27-11-21","CreatedTime":"18:01:06","SaleDate":"27-11-21","SaleTime":"18:01:46","Typed":"3800226520859","ItemGID":"100739829","BarCode":"3800226520859","BaseItemName":"КИСЕЛО МЛЯКО САЯНА 2% БДС 400ГР.","PackCoeff":"1","ItemName":"КИСЕЛО МЛЯКО САЯНА 2% БДС 400ГР.                                      ","Measure":"БР.","Quantity":"1.000","VendorPrice":"0.6156","ClientSurcharge":"0.00","ClientPrice":"0.70","PackDiscount":"0","ClientPriceBase":"0.58","Price":"0.70","DiscountValue":"0.00","DiscountType":"0","TotalBase":"0.58","VATRate":"20.00","TotalVAT":"0.12","Total":"0.70","IsCancelled":"не"}],"Cancellations":[],"Reversals":[],"Payments":[{"GID":"303107247","ParentGID":"302400686","SaleUniqueID":"DT652293-0003-0400686","FiscalDeviceID":"DT652293","UserID":"3","CreatedDate":"27-11-21","CompletedDate":"27-11-21","Due":"10.45","PaymentDate":"27-11-21","PaymentType":"cash","PaymentBase":"8.71","PaymentVAT":"1.74","Payment":"10.45"},{"GID":"303107248","ParentGID":"302400686","SaleUniqueID":"DT652293-0003-0400686","FiscalDeviceID":"DT652293","UserID":"3","CreatedDate":"27-11-21","CompletedDate":"27-11-21","Due":"10.45","PaymentDate":"27-11-21","PaymentType":"returned","PaymentBase":"0.00","PaymentVAT":"0.00","Payment":"0.00"}]}