{"GID":"302287111","StoreID":"110","StoreName":"МАГАЗИН АНЕТ 4 бл.548","WorkstationID":"2","FiscalDeviceID":"DT652293","UserGID":"8","SaleID":"287111","SaleUniqueID":"DT652293-0008-0287111","ReceiptID":"735099","ClientGID":"1","ClientName":"КЛИЕНТ НА МАГАЗИН АНЕТ 4","ClientTaxNumberType":"0","ClientTaxNumber":"","ClientAddress":"","ClientReceiver":"","ClientBuyer":"","ClientVIPStatus":"","ClientSurcharge":"0.00","InvoiceID":"","InvoiceDate":"","CreatedDate":"26-04-21","CreatedTime":"13:04:38","CompletedDate":"26-04-21","CompletedTime":"13:05:03","TotalBase":"0.00","Discount":"0.00","TotalVAT":"0.00","Due":"6.59","CashPayment":"20.70","VoucherPayment":"0.00","CardPayment":"0.00","Returned":"14.11","Stage":"приключена","Details":[{"GID":"305089916","ParentGID":"302287111","SaleUniqueID":"DT652293-0008-0287111","UserGID":"8","CreatedDate":"26-04-21","CreatedTime":"13:04:38","SaleDate":"26-04-21","SaleTime":"13:04:38","Typed":"3800069401315","ItemGID":"9667","BarCode":"3800069401315","BaseItemName":"МЕДИКС ЗА ПАРКЕТ И ЛАМИНАТ 1.5Л.","PackCoeff":"1","ItemName":"МЕДИКС ЗА ПАРКЕТ И ЛАМИНАТ 1.5Л.                                      ","Measure":"БР.","Quantity":"1.000","VendorPrice":"3.0130","ClientSurcharge":"0.00","ClientPrice":"3.59","PackDiscount":"0","ClientPriceBase":"2.99","Price":"3.59","DiscountValue":"0.00","DiscountType":"0","TotalBase":"2.99","VATRate":"20.00","TotalVAT":"0.60","Total":"3.59","IsCancelled":"не"},{"GID":"305089918","ParentGID":"302287111","SaleUniqueID":"DT652293-0008-0287111","UserGID":"8","CreatedDate":"26-04-21","CreatedTime":"13:04:38","SaleDate":"26-04-21","SaleTime":"13:04:40","Typed":"3800204650172","ItemGID":"347","BarCode":"3800204650172","BaseItemName":"ОЛИО БУРГАСПАК 1ЛИТЪР","PackCoeff":"1","ItemName":"ОЛИО БУРГАСПАК 1ЛИТЪР                                                 ","Measure":"БР.","Quantity":"1.000","VendorPrice":"2.9000","ClientSurcharge":"0.00","ClientPrice":"3.00","PackDiscount":"0","ClientPriceBase":"2.50","Price":"3.00","DiscountValue":"0.00","DiscountType":"0","TotalBase":"2.50","VATRate":"20.00","TotalVAT":"0.50","Total":"3.00","IsCancelled":"не"}],"Cancellations":[],"Reversals":[],"Payments":[{"GID":"302886893","ParentGID":"302287111","SaleUniqueID":"DT652293-0008-0287111","FiscalDeviceID":"DT652293","UserID":"8","CreatedDate":"26-04-21","CompletedDate":"26-04-21","Due":"6.59","PaymentDate":"26-04-21","PaymentType":"cash","PaymentBase":"17.25","PaymentVAT":"3.45","Payment":"20.70"},{"GID":"302886894","ParentGID":"302287111","SaleUniqueID":"DT652293-0008-0287111","FiscalDeviceID":"DT652293","UserID":"8","CreatedDate":"26-04-21","CompletedDate":"26-04-21","Due":"6.59","PaymentDate":"26-04-21","PaymentType":"returned","PaymentBase":"11.76","PaymentVAT":"2.35","Payment":"14.11"}]}