{"GID":"302848612","StoreID":"110","StoreName":"МАГАЗИН АНЕТ 4 бл.548","WorkstationID":"2","FiscalDeviceID":"DT938710","UserGID":"11","SaleID":"848612","SaleUniqueID":"DT938710-0011-0848612","ReceiptID":"329426","ClientGID":"1","ClientName":"КЛИЕНТ НА МАГАЗИН АНЕТ 4","ClientTaxNumberType":"0","ClientTaxNumber":"","ClientAddress":"","ClientReceiver":"","ClientBuyer":"","ClientVIPStatus":"","ClientSurcharge":"0.00","InvoiceID":"","InvoiceDate":"","CreatedDate":"21-12-23","CreatedTime":"12:42:48","CompletedDate":"21-12-23","CompletedTime":"12:43:52","TotalBase":"0.00","Discount":"0.00","TotalVAT":"0.00","Due":"44.67","CashPayment":"50.00","VoucherPayment":"0.00","CardPayment":"0.00","Returned":"5.33","Stage":"приключена","Details":[{"GID":"310752688","ParentGID":"302848612","SaleUniqueID":"DT938710-0011-0848612","UserGID":"11","CreatedDate":"21-12-23","CreatedTime":"12:42:48","SaleDate":"21-12-23","SaleTime":"12:42:48","Typed":"3800024048364","ItemGID":"1200","BarCode":"3800024048364","BaseItemName":"ПРАХ ЕХО САВЕКС 1.800\/2КГ.ВИДОВЕ","PackCoeff":"1","ItemName":"ПРАХ ЕХО САВЕКС 1.800\/2КГ.ВИДОВЕ                                      ","Measure":"БР.","Quantity":"1.000","VendorPrice":"6.1537","ClientSurcharge":"0.00","ClientPrice":"7.39","PackDiscount":"0","ClientPriceBase":"6.16","Price":"7.39","DiscountValue":"0.00","DiscountType":"0","TotalBase":"6.16","VATRate":"20.00","TotalVAT":"1.23","Total":"7.39","IsCancelled":"не"},{"GID":"310752690","ParentGID":"302848612","SaleUniqueID":"DT938710-0011-0848612","UserGID":"11","CreatedDate":"21-12-23","CreatedTime":"12:42:48","SaleDate":"21-12-23","SaleTime":"12:42:50","Typed":"888","ItemGID":"100479935","BarCode":"3800077011285","BaseItemName":"ТОРБИЧКА АНЕТ 30\/60","PackCoeff":"1","ItemName":"ТОРБИЧКА АНЕТ 30\/60                                                   ","Measure":"БР.","Quantity":"1.000","VendorPrice":"0.0978","ClientSurcharge":"0.00","ClientPrice":"0.12","PackDiscount":"0","ClientPriceBase":"0.10","Price":"0.12","DiscountValue":"0.00","DiscountType":"0","TotalBase":"0.10","VATRate":"20.00","TotalVAT":"0.02","Total":"0.12","IsCancelled":"не"},{"GID":"310752692","ParentGID":"302848612","SaleUniqueID":"DT938710-0011-0848612","UserGID":"11","CreatedDate":"21-12-23","CreatedTime":"12:42:48","SaleDate":"21-12-23","SaleTime":"12:42:53","Typed":"3800214420512","ItemGID":"10149","BarCode":"3800214420512","BaseItemName":"ЛОЗОВ ЛИСТ 680ГР.АРИВА","PackCoeff":"1","ItemName":"ЛОЗОВ ЛИСТ 680ГР.АРИВА                                                ","Measure":"БР.","Quantity":"1.000","VendorPrice":"2.9617","ClientSurcharge":"0.00","ClientPrice":"3.50","PackDiscount":"0","ClientPriceBase":"2.92","Price":"3.50","DiscountValue":"0.00","DiscountType":"0","TotalBase":"2.92","VATRate":"20.00","TotalVAT":"0.58","Total":"3.50","IsCancelled":"не"},{"GID":"310752694","ParentGID":"302848612","SaleUniqueID":"DT938710-0011-0848612","UserGID":"11","CreatedDate":"21-12-23","CreatedTime":"12:42:48","SaleDate":"21-12-23","SaleTime":"12:42:55","Typed":"59459217","ItemGID":"6378","BarCode":"59459217","BaseItemName":"ДАНОНИНО 4Х50ГР.\/ВИДОВЕ","PackCoeff":"1","ItemName":"ДАНОНИНО 4Х50ГР.\/ВИДОВЕ                                               ","Measure":"БР.","Quantity":"1.000","VendorPrice":"2.9600","ClientSurcharge":"0.00","ClientPrice":"3.45","PackDiscount":"0","ClientPriceBase":"2.88","Price":"3.45","DiscountValue":"0.00","DiscountType":"0","TotalBase":"2.88","VATRate":"20.00","TotalVAT":"0.57","Total":"3.45","IsCancelled":"не"},{"GID":"310752696","ParentGID":"302848612","SaleUniqueID":"DT938710-0011-0848612","UserGID":"11","CreatedDate":"21-12-23","CreatedTime":"12:42:48","SaleDate":"21-12-23","SaleTime":"12:42:57","Typed":"3800200758230","ItemGID":"100958950","BarCode":"3800200758230","BaseItemName":"САЛАТА РУСКА 400ГР.КРИСТЕЛ","PackCoeff":"1","ItemName":"САЛАТА РУСКА 400ГР.КРИСТЕЛ                                            ","Measure":"БР.","Quantity":"1.000","VendorPrice":"2.3400","ClientSurcharge":"0.00","ClientPrice":"2.79","PackDiscount":"0","ClientPriceBase":"2.33","Price":"2.79","DiscountValue":"0.00","DiscountType":"0","TotalBase":"2.33","VATRate":"20.00","TotalVAT":"0.46","Total":"2.79","IsCancelled":"не"},{"GID":"310752698","ParentGID":"302848612","SaleUniqueID":"DT938710-0011-0848612","UserGID":"11","CreatedDate":"21-12-23","CreatedTime":"12:42:48","SaleDate":"21-12-23","SaleTime":"12:42:59","Typed":"7622210544179","ItemGID":"100702169","BarCode":"7622210544179","BaseItemName":"ШОК.МИЛКА ОРЕО БЯЛ 100ГР.","PackCoeff":"1","ItemName":"ШОК.МИЛКА ОРЕО БЯЛ 100ГР.                                             ","Measure":"БР.","Quantity":"1.000","VendorPrice":"1.5748","ClientSurcharge":"0.00","ClientPrice":"1.89","PackDiscount":"0","ClientPriceBase":"1.58","Price":"1.89","DiscountValue":"0.00","DiscountType":"0","TotalBase":"1.58","VATRate":"20.00","TotalVAT":"0.31","Total":"1.89","IsCancelled":"не"},{"GID":"310752700","ParentGID":"302848612","SaleUniqueID":"DT938710-0011-0848612","UserGID":"11","CreatedDate":"21-12-23","CreatedTime":"12:42:48","SaleDate":"21-12-23","SaleTime":"12:43:01","Typed":"40084794","ItemGID":"8309","BarCode":"40084794","BaseItemName":"ШОК.ДЕСЕРТ КИНДЕР С МЛЕЧЕН ПЪЛНЕЖ ШНИТЕ","PackCoeff":"1","ItemName":"ШОК.ДЕСЕРТ КИНДЕР С МЛЕЧЕН ПЪЛНЕЖ ШНИТЕ                               ","Measure":"БР.","Quantity":"1.000","VendorPrice":"1.0098","ClientSurcharge":"0.00","ClientPrice":"1.18","PackDiscount":"0","ClientPriceBase":"0.98","Price":"1.18","DiscountValue":"0.00","DiscountType":"0","TotalBase":"0.98","VATRate":"20.00","TotalVAT":"0.20","Total":"1.18","IsCancelled":"не"},{"GID":"310752702","ParentGID":"302848612","SaleUniqueID":"DT938710-0011-0848612","UserGID":"11","CreatedDate":"21-12-23","CreatedTime":"12:42:48","SaleDate":"21-12-23","SaleTime":"12:43:03","Typed":"3800200758216","ItemGID":"100958953","BarCode":"3800200758216","BaseItemName":"САЛАТА СНЕЖАНКА 400ГР.КРИСТЕЛ","PackCoeff":"1","ItemName":"САЛАТА СНЕЖАНКА 400ГР.КРИСТЕЛ                                         ","Measure":"БР.","Quantity":"1.000","VendorPrice":"2.9700","ClientSurcharge":"0.00","ClientPrice":"3.55","PackDiscount":"0","ClientPriceBase":"2.96","Price":"3.55","DiscountValue":"0.00","DiscountType":"0","TotalBase":"2.96","VATRate":"20.00","TotalVAT":"0.59","Total":"3.55","IsCancelled":"не"},{"GID":"310752704","ParentGID":"302848612","SaleUniqueID":"DT938710-0011-0848612","UserGID":"11","CreatedDate":"21-12-23","CreatedTime":"12:42:48","SaleDate":"21-12-23","SaleTime":"12:43:06","Typed":"3800110300611","ItemGID":"100134647","BarCode":"3800110300611","BaseItemName":"КИС.МЛЯКО ДОМЛЯН 4.5% 500ГР.","PackCoeff":"1","ItemName":"КИС.МЛЯКО ДОМЛЯН 4.5% 500ГР.                                          ","Measure":"БР.","Quantity":"1.000","VendorPrice":"1.4208","ClientSurcharge":"0.00","ClientPrice":"1.65","PackDiscount":"0","ClientPriceBase":"1.38","Price":"1.65","DiscountValue":"0.00","DiscountType":"0","TotalBase":"1.38","VATRate":"20.00","TotalVAT":"0.27","Total":"1.65","IsCancelled":"не"},{"GID":"310752706","ParentGID":"302848612","SaleUniqueID":"DT938710-0011-0848612","UserGID":"11","CreatedDate":"21-12-23","CreatedTime":"12:42:48","SaleDate":"21-12-23","SaleTime":"12:43:09","Typed":"3800232270014","ItemGID":"101032909","BarCode":"3800232270014","BaseItemName":"КАЙМА 0.500КГ. РОДОПА ТРОЯН","PackCoeff":"1","ItemName":"КАЙМА 0.500КГ. РОДОПА ТРОЯН                                           ","Measure":"БР.","Quantity":"1.000","VendorPrice":"5.1000","ClientSurcharge":"0.00","ClientPrice":"5.99","PackDiscount":"0","ClientPriceBase":"4.99","Price":"5.99","DiscountValue":"0.00","DiscountType":"0","TotalBase":"4.99","VATRate":"20.00","TotalVAT":"1.00","Total":"5.99","IsCancelled":"не"},{"GID":"310752708","ParentGID":"302848612","SaleUniqueID":"DT938710-0011-0848612","UserGID":"11","CreatedDate":"21-12-23","CreatedTime":"12:42:48","SaleDate":"21-12-23","SaleTime":"12:43:12","Typed":"1900005002322","ItemGID":"2496","BarCode":"5","BaseItemName":"КРЕНВИРШ КЕН КГ..","PackCoeff":"1","ItemName":"КРЕНВИРШ КЕН КГ..                                                     ","Measure":"КГ.","Quantity":"0.232","VendorPrice":"9.4049","ClientSurcharge":"0.00","ClientPrice":"10.99","PackDiscount":"0","ClientPriceBase":"9.16","Price":"10.99","DiscountValue":"0.00","DiscountType":"0","TotalBase":"2.13","VATRate":"20.00","TotalVAT":"0.42","Total":"2.55","IsCancelled":"не"},{"GID":"310752710","ParentGID":"302848612","SaleUniqueID":"DT938710-0011-0848612","UserGID":"11","CreatedDate":"21-12-23","CreatedTime":"12:42:48","SaleDate":"21-12-23","SaleTime":"12:43:14","Typed":"5201360517329","ItemGID":"100604605","BarCode":"5201360517329","BaseItemName":"КРОАСАН МАКС БИСКВИТКА ВАНИЛИЯ 92ГР.","PackCoeff":"1","ItemName":"КРОАСАН МАКС БИСКВИТКА ВАНИЛИЯ 92ГР.                                  ","Measure":"БР.","Quantity":"1.000","VendorPrice":"1.0901","ClientSurcharge":"0.00","ClientPrice":"1.29","PackDiscount":"0","ClientPriceBase":"1.08","Price":"1.29","DiscountValue":"0.00","DiscountType":"0","TotalBase":"1.08","VATRate":"20.00","TotalVAT":"0.21","Total":"1.29","IsCancelled":"не"},{"GID":"310752712","ParentGID":"302848612","SaleUniqueID":"DT938710-0011-0848612","UserGID":"11","CreatedDate":"21-12-23","CreatedTime":"12:42:48","SaleDate":"21-12-23","SaleTime":"12:43:16","Typed":"3800204650158","ItemGID":"2120","BarCode":"3800204650158","BaseItemName":"СЛЪНЧЕВ ОРИЗ 500ГР.БУРГАСПАК","PackCoeff":"1","ItemName":"СЛЪНЧЕВ ОРИЗ 500ГР.БУРГАСПАК                                          ","Measure":"БР.","Quantity":"1.000","VendorPrice":"1.3000","ClientSurcharge":"0.00","ClientPrice":"1.55","PackDiscount":"0","ClientPriceBase":"1.29","Price":"1.55","DiscountValue":"0.00","DiscountType":"0","TotalBase":"1.29","VATRate":"20.00","TotalVAT":"0.26","Total":"1.55","IsCancelled":"не"},{"GID":"310752714","ParentGID":"302848612","SaleUniqueID":"DT938710-0011-0848612","UserGID":"11","CreatedDate":"21-12-23","CreatedTime":"12:42:48","SaleDate":"21-12-23","SaleTime":"12:43:17","Typed":"90426230","ItemGID":"100618115","BarCode":"90426230","BaseItemName":"МЛЕЧЕН ДЕСЕРТ МИЛКА 32ГР.","PackCoeff":"1","ItemName":"МЛЕЧЕН ДЕСЕРТ МИЛКА 32ГР.                                             ","Measure":"БР.","Quantity":"1.000","VendorPrice":"1.1900","ClientSurcharge":"0.00","ClientPrice":"1.40","PackDiscount":"0","ClientPriceBase":"1.17","Price":"1.40","DiscountValue":"0.00","DiscountType":"0","TotalBase":"1.17","VATRate":"20.00","TotalVAT":"0.23","Total":"1.40","IsCancelled":"не"},{"GID":"310752716","ParentGID":"302848612","SaleUniqueID":"DT938710-0011-0848612","UserGID":"11","CreatedDate":"21-12-23","CreatedTime":"12:42:48","SaleDate":"21-12-23","SaleTime":"12:43:19","Typed":"3800005000831","ItemGID":"14445","BarCode":"3800005000831","BaseItemName":"БИСВИТЕНА КАША С БИФИДУС СЛЪНЧО 200ГР.","PackCoeff":"1","ItemName":"БИСВИТЕНА КАША С БИФИДУС СЛЪНЧО 200ГР.                                ","Measure":"БР.","Quantity":"1.000","VendorPrice":"4.2110","ClientSurcharge":"0.00","ClientPrice":"4.85","PackDiscount":"0","ClientPriceBase":"4.45","Price":"4.85","DiscountValue":"0.00","DiscountType":"0","TotalBase":"4.45","VATRate":"9.00","TotalVAT":"0.40","Total":"4.85","IsCancelled":"не"},{"GID":"310752718","ParentGID":"302848612","SaleUniqueID":"DT938710-0011-0848612","UserGID":"11","CreatedDate":"21-12-23","CreatedTime":"12:42:48","SaleDate":"21-12-23","SaleTime":"12:43:24","Typed":"100","ItemGID":"12084","BarCode":"100","BaseItemName":"ХЛЯБ БЯЛ БУРГАСХЛЯБ 600ГР.","PackCoeff":"1","ItemName":"ХЛЯБ БЯЛ БУРГАСХЛЯБ 600ГР.                                            ","Measure":"БР.","Quantity":"1.000","VendorPrice":"1.3580","ClientSurcharge":"0.00","ClientPrice":"1.52","PackDiscount":"0","ClientPriceBase":"1.52","Price":"1.52","DiscountValue":"0.00","DiscountType":"0","TotalBase":"1.52","VATRate":"0.00","TotalVAT":"0.00","Total":"1.52","IsCancelled":"не"}],"Cancellations":[],"Reversals":[],"Payments":[{"GID":"303976006","ParentGID":"302848612","SaleUniqueID":"DT938710-0011-0848612","FiscalDeviceID":"DT938710","UserID":"11","CreatedDate":"21-12-23","CompletedDate":"21-12-23","Due":"44.67","PaymentDate":"21-12-23","PaymentType":"cash","PaymentBase":"41.67","PaymentVAT":"8.33","Payment":"50.00"},{"GID":"303976007","ParentGID":"302848612","SaleUniqueID":"DT938710-0011-0848612","FiscalDeviceID":"DT938710","UserID":"11","CreatedDate":"21-12-23","CompletedDate":"21-12-23","Due":"44.67","PaymentDate":"21-12-23","PaymentType":"returned","PaymentBase":"4.44","PaymentVAT":"0.89","Payment":"5.33"}]}